setup.py
SnowLang/__init__.py
SnowLang.egg-info/PKG-INFO
SnowLang.egg-info/SOURCES.txt
SnowLang.egg-info/dependency_links.txt
SnowLang.egg-info/requires.txt
SnowLang.egg-info/top_level.txt
SnowLang/app/__init__.py
SnowLang/app/app.py
SnowLang/app/cli.py
SnowLang/compiler/__init__.py
SnowLang/compiler/compiler.py
SnowLang/errors/__init__.py
SnowLang/errors/error.py
SnowLang/errors/pointer.py
SnowLang/interpreter/__init__.py
SnowLang/interpreter/interpreter.py
SnowLang/interpreter/types.py
SnowLang/lexer/__init__.py
SnowLang/lexer/lexer.py
SnowLang/lexer/tokens.py
SnowLang/lexer/cogs/__init__.py
SnowLang/lexer/cogs/identifier.py
SnowLang/lexer/cogs/keywords.py
SnowLang/lexer/cogs/numbers.py
SnowLang/lexer/cogs/operators.py
SnowLang/lexer/cogs/symbols.py
SnowLang/parser/__init__.py
SnowLang/parser/nodes.py
SnowLang/parser/parser.py
docs/__init__.py
test/test.py