Metadata-Version: 2.1
Name: SnowLang
Version: 0.5.1.8
Summary: Snow Programming Language for beginners
Home-page: https://github.com/SnowballSH/Snow-lang
Author: SnowballSH
License: UNKNOWN
Download-URL: https://github.com/SnowballSH/Snow-lang/archive/v0.5.1.8.tar.gz
Platform: UNKNOWN
Classifier: Development Status :: 5 - Production/Stable
Classifier: Intended Audience :: Developers
Classifier: License :: OSI Approved :: MIT License
Classifier: Natural Language :: English
Classifier: Operating System :: OS Independent
Classifier: Programming Language :: Python :: 3.6
Classifier: Programming Language :: Python :: 3.7
Classifier: Programming Language :: Python :: 3.8
Classifier: Programming Language :: Python :: 3.9
Classifier: Topic :: Artistic Software
Requires-Python: >=3.6
